<?xml version="1.0" encoding="UTF-8" standalone="yes"?>
<ProxyEndpoint name="default">
    <Description/>
    <FaultRules/>
    <PreFlow name="PreFlow">
        <Request>
            <Step>
                <Name>__extract-statistics-request__</Name>
            </Step>
            <Step>
                <Name>__collect-statistics-request__</Name>
            </Step>
        </Request>
        <Response>
        </Response>
    </PreFlow>
    <PostFlow name="PostFlow">
        <Request/>
        <Response/>
    </PostFlow>
    <Flows/>
    <HTTPProxyConnection>
        <BasePath>/hw5</BasePath>
        <Properties/>
        <VirtualHost>default</VirtualHost>
        <VirtualHost>secure</VirtualHost>
    </HTTPProxyConnection>
    <RouteRule name="default">
        <TargetEndpoint>default</TargetEndpoint>
    </RouteRule>
</ProxyEndpoint>